MANIFEST.in
README.rst
kerberos_sspi.py
setup.py
kerberos_sspi.egg-info/PKG-INFO
kerberos_sspi.egg-info/SOURCES.txt
kerberos_sspi.egg-info/dependency_links.txt
kerberos_sspi.egg-info/requires.txt
kerberos_sspi.egg-info/top_level.txt