Metadata-Version: 1.1
Name: kerberos-sspi
Version: 0.2
Summary: Kerberos high-level windows interface
Home-page: https://github.com/may-day/kerberos-sspi
Author: Norman Krämer
Author-email: kraemer.norman@gmail.com
License: Apache Software License 2.0
Platform: UNKNOWN
Classifier: License :: OSI Approved :: Apache Software License
Classifier: Programming Language :: Python :: 2
Classifier: Programming Language :: Python :: 3
Classifier: Topic :: Software Development :: Libraries :: Python Modules
Classifier: Topic :: System :: Systems Administration :: Authentication/Directory
